goforge/__init__.py
goforge/__main__.py
goforge/config_parser.py
goforge/file_manager/__init__.py
goforge/file_manager/file_manager.py
goforge/main.py
goforge/writer/__init__.py
goforge/writer/handler_maker.py
goforge/writer/server_maker.py
goforge/writer/sql_maker.py
goforge-0.2.0.dist-info/METADATA
goforge-0.2.0.dist-info/WHEEL
goforge-0.2.0.dist-info/entry_points.txt
goforge-0.2.0.dist-info/RECORD
