Metadata-Version: 2.1
Name: goforge
Version: 0.2.0
Summary: generate entire CRUD backend for golang echo and postgres with one command
Keywords: code generator,golang echo,postgres
Author: Prashant Bhatkal
Author-email: prashantbhatkal2000@gmail.com
Requires-Python: >=3.7,<4.0
Classifier: Programming Language :: Python :: 3
Classifier: Programming Language :: Python :: 3.7
Classifier: Programming Language :: Python :: 3.8
Classifier: Programming Language :: Python :: 3.9
Classifier: Programming Language :: Python :: 3.10
Classifier: Programming Language :: Python :: 3.11
Classifier: Programming Language :: Python :: 3.12
Requires-Dist: Jinja2 (>=3.1.2)
Requires-Dist: pyyaml (>=5.4.1)
